{"stats":{"minecraft:custom":{"minecraft:time_since_rest":6323,"minecraft:crouch_one_cm":17,"minecraft:play_time":6323,"minecraft:sprint_one_cm":2644,"minecraft:damage_absorbed":57,"minecraft:damage_taken":164,"minecraft:walk_one_cm":7569,"minecraft:sneak_time":40,"minecraft:mob_kills":21,"minecraft:jump":124,"minecraft:damage_dealt":3714,"minecraft:leave_game":1,"minecraft:time_since_death":6323,"minecraft:total_world_time":6350,"minecraft:damage_resisted":23,"minecraft:fall_one_cm":1003,"minecraft:fly_one_cm":13569},"minecraft:picked_up":{"minecraft:oak_slab":6,"minecraft:rotten_flesh":27,"minecraft:stone_bricks":1,"minecraft:oak_log":2,"minecraft:oak_planks":2},"minecraft:used":{"minecraft:deepslate_bricks":1,"minecraft:stone_bricks":1,"minecraft:oak_log":4,"minecraft:diamond_sword":21,"minecraft:oak_slab":10,"minecraft:oak_planks":5,"minecraft:deepslate_brick_slab":3,"minecraft:enchanted_golden_apple":1},"minecraft:killed":{"minecraft:zombie":21}},"DataVersion":3955}