{
  "waveNumber": 1,
  "name": "wave.1.name",
  "startMessage": "wave.1.startMessage",
  "endMessage": "wave.1.endMessage",
  "mobs": [
    {
      "type": "minecraft:zombie",
      "count": 6,
      "displayName": "",
      "healthMultiplier": 1.0,
      "damageMultiplier": 1.0,
      "speedMultiplier": 1.0,
      "canBreakBlocks": true,
      "breakLevel": "stone",
      "canClimb": true,
      "climbHeight": 1.5,
      "canSwim": true,
      "isMiniZombieVanilla": false,
      "isMiniZombieBoosted": false,
      "isMiniZombieKamikaze": false,
      "isKamikaze": false,
      "isHealer": false,
      "healIntervalTicks": 40,
      "healAmount": 3.0,
      "healRadius": 8.0,
      "isShielder": false,
      "isSummoner": false,
      "summonCount": 3,
      "isBoss": false
    },
    {
      "type": "minecraft:zombie",
      "count": 5,
      "displayName": "",
      "healthMultiplier": 1.0,
      "damageMultiplier": 1.0,
      "speedMultiplier": 1.0,
      "canBreakBlocks": false,
      "breakLevel": "wood",
      "canClimb": false,
      "climbHeight": 1.5,
      "canSwim": false,
      "isMiniZombieVanilla": true,
      "isMiniZombieBoosted": false,
      "isMiniZombieKamikaze": false,
      "isKamikaze": false,
      "isHealer": false,
      "healIntervalTicks": 40,
      "healAmount": 3.0,
      "healRadius": 8.0,
      "isShielder": false,
      "isSummoner": false,
      "summonCount": 3,
      "isBoss": false
    }
  ],
  "durationSeconds": 180,
  "spawnInWater": false,
  "hasBoss": false,
  "bossType": "",
  "bossName": "",
  "spawnRadiusOverride": -1,
  "rewardCommands": [
    "give %player% minecraft:arrow 10",
    "effect give %player% minecraft:regeneration 10 1"
  ],
  "autoNextWave": false,
  "autoNextDelaySec": -1,
  "objectiveX": -2147483648,
  "objectiveY": -2147483648,
  "objectiveZ": -2147483648,
  "objectiveSpeed": 1.0,
  "rallyX": -2147483648,
  "rallyY": -2147483648,
  "rallyZ": -2147483648,
  "rallyRadius": 8
}